Metadata-Version: 1.1
Name: kubespray
Version: 0.5.1
Summary: Kubespray kubernetes cluster deployment
Home-page: https://github.com/kubespray/kubespray-cli
Author: Smaine Kahlouch
Author-email: smainklh@gmail.com
License: GPLv3
Keywords: kubespray
Platform: UNKNOWN
Classifier: Development Status :: 2 - Pre-Alpha
Classifier: Intended Audience :: Developers
Classifier: Natural Language :: English
Classifier: Programming Language :: Python :: 2
Classifier: Programming Language :: Python :: 2.7
